instructionMemo.v
module instructionMemory(
    input  [31:0] add,
    output reg [31:0] instruction
);

    // 256 words = 1KB of instruction memory
    // program.mem must be in the same directory as your simulation run
    reg [31:0] mem [0:255];

    initial begin
        $readmemh("program.mem", mem);
    end

    always @(*) begin
        instruction = mem[add >> 2];  // byte address → word index
    end

endmodule

src/pc_counter.v
module pc_counter
(input [31:0]PcIn,
input clk,
input reset,
output  reg [31:0]PcNxt);

always@(posedge clk)begin
    if(reset)
    PcNxt<=0;
    else
    PcNxt<=PcIn+4;
end
endmodule

fetch_tb.v
`timescale 1ns/1ps

module fetch_tb;

reg clk;
reg reset;

wire [31:0] PcNxt;
wire [31:0] instruction;

// Instantiate PC
pc_counter pc_inst (
    .PcIn(PcNxt),   // feedback
    .clk(clk),
    .reset(reset),
    .PcNxt(PcNxt)
);

// Instantiate Instruction Memory
instructionMemory imem_inst (
    .add(PcNxt),
    .instruction(instruction)
);

// Clock generation: 10ns period
always #5 clk = ~clk;

initial begin
    $dumpfile("fetch_stage.vcd");
    $dumpvars(0, fetch_tb);

    clk = 0;
    reset = 1;

    #10;          // hold reset
    reset = 0;    // release reset

    #80;          // run for some cycles

    $finish;
end

endmodule

fetch_stage.vcd
$date
	Tue Feb 17 15:55:56 2026
$end
$version
	Icarus Verilog
$end
$timescale
	1ps
$end
$scope module fetch_tb $end
$var wire 32 ! instruction [31:0] $end
$var wire 32 " PcNxt [31:0] $end
$var reg 1 # clk $end
$var reg 1 $ reset $end
$scope module imem_inst $end
$var wire 32 % add [31:0] $end
$var reg 32 & instruction [31:0] $end
$upscope $end
$scope module pc_inst $end
$var wire 1 # clk $end
$var wire 1 $ reset $end
$var wire 32 ' PcIn [31:0] $end
$var reg 32 ( PcNxt [31:0] $end
$upscope $end
$upscope $end
$enddefinitions $end
$comment Show the parameter values. $end
$dumpall
$end
#0
$dumpvars
bx (
bx '
bx &
bx %
1$
0#
bx "
bx !
$end
#5000
b10101100101011001010110010101100 !
b10101100101011001010110010101100 &
b0 "
b0 %
b0 '
b0 (
1#
#10000
0#
0$
#15000
b1010111000111001010101100011100 !
b1010111000111001010101100011100 &
b100 "
b100 %
b100 '
b100 (
1#
#20000
0#
#25000
b11100011001010101111000011001101 !
b11100011001010101111000011001101 &
b1000 "
b1000 %
b1000 '
b1000 (
1#
#30000
0#
#35000
b0 !
b0 &
b1100 "
b1100 %
b1100 '
b1100 (
1#
#40000
0#
#45000
b10000 "
b10000 %
b10000 '
b10000 (
1#
#50000
0#
#55000
b10100 "
b10100 %
b10100 '
b10100 (
1#
#60000
0#
#65000
b11000 "
b11000 %
b11000 '
b11000 (
1#
#70000
0#
#75000
b11100 "
b11100 %
b11100 '
b11100 (
1#
#80000
0#
#85000
b100000 "
b100000 %
b100000 '
b100000 (
1#
