src/DataMemo.v
module DataMemo (
    input  clk,
    input  mem_read,
    input  mem_write,
    input [31:0] address,
    input [31:0] write_data,
    output [31:0] read_data
);

    reg [31:0] mem [0:1023];

    // Asynchronous read
    assign read_data = (mem_read) ? mem[address[11:2]] : 32'b0;

    // Synchronous write
    always @(posedge clk) begin
        if (mem_write)
            mem[address[11:2]] <= write_data;
    end

endmodule

registerFile.v
module registerFile 
(
input [4:0] rs1_addr,
input [4:0] rs2_addr,
input [4:0] rd_addr,
input clk,
input [31:0] WriteData,
input RegWrite,

output reg[31:0] ReadData1,
output reg[31:0] ReadData2

);

reg [31:0] registers [0:31];
//making each register empty initially so no garbage value is thrown generally good practice

integer i;
initial begin
    for(i=0; i<32;i=i+1)begin
        registers[i]=0;
    end    
end
//combinational part
always@(*)begin
    ReadData1= registers[rs1_addr];
    ReadData2= registers[rs2_addr];
end
//sequential part 
always@(posedge clk)begin
    if(RegWrite && rd_addr != 5'd0)begin
        registers[rd_addr] <= WriteData;
    end
end

endmodule

src/AluControl.v
module AluControl(
    input [1:0] ALUOp,
    input [2:0] funct3,
    input funct7,
    input ALUSrc,
    output reg [3:0] sel
);

always @(*) begin
    case(ALUOp)
        2'b00: sel = 4'd0;  // LOAD/STORE always ADD
        2'b01: sel = 4'd1;  // BRANCH always SUB

        2'b10: case(funct3)
            3'b000: sel = (funct7 && !ALUSrc) ? 4'd1 : 4'd0; // SUB only R-type, ADDI always ADD
            3'b111: sel = 4'd2;  // AND/ANDI
            3'b110: sel = 4'd3;  // OR/ORI
            3'b100: sel = 4'd4;  // XOR/XORI
            3'b001: sel = 4'd5;  // SLL/SLLI
            3'b101: sel = (funct7) ? 4'd7 : 4'd6; // SRA/SRAI vs SRL/SRLI
            3'b010: sel = 4'd8;  // SLT/SLTI
            3'b011: sel = 4'd9;  // SLTU/SLTIU
            default: sel = 4'd0;
        endcase

        default: sel = 4'd0;
    endcase
end

endmodule

alu.v
module alu(
    input  [31:0] rs1_Value,
    input  [31:0] rs2_Value,
    input  [31:0] immediate,
    input  [3:0]  sel,        // changed to 4 bits
    input         AluSrc,
    output reg    zeroflag,
    output reg [31:0] aluResult
);

    wire [31:0] b;

    assign b = (AluSrc == 1'b0) ? rs2_Value : immediate;

    always @(*) begin
        case(sel)

            4'd0:  aluResult = rs1_Value + b;        // add
            4'd1:  aluResult = rs1_Value - b;        // sub
            4'd2:  aluResult = rs1_Value & b;        // and
            4'd3:  aluResult = rs1_Value | b;        // or
            4'd4:  aluResult = rs1_Value ^ b;        // xor
            4'd5:  aluResult = rs1_Value << b[4:0];       // shift left by 4
            4'd6:  aluResult = rs1_Value >> b[4:0];      // shift right by 4 srl
            4'd7: aluResult=($signed(rs1_Value)) >>> b[4:0]   ;       // SRA shift right arithmatic
            4'd8: aluResult=($signed(rs1_Value)<$signed(b))? 32'd1:32'd0;       // SLT set less than
            
            default: aluResult = 32'd0;

        endcase

        zeroflag = (aluResult == 32'd0);

    end

endmodule

decoder.v
module decoder(
    input  [31:0] instruction,

    output reg [6:0] opcode,
    output reg [4:0] rd_addr,
    output reg [2:0] funct3,
    output reg [4:0] rs1_addr,
    output reg [4:0] rs2_addr,
    output reg funct7,

    output reg RegWrite,
    output reg MemRead,
    output reg MemWrite,
    output reg MemtoReg,
    output reg ALUSrc,
    output reg Branch,
    output reg [1:0] ALUOp
);

always @(*) begin

    // Field Extraction 
    opcode = instruction[6:0];
    rd_addr     = instruction[11:7];
    funct3 = instruction[14:12];
    rs1_addr    = instruction[19:15];
    rs2_addr    = instruction[24:20];
    funct7 = instruction[30];

    //  Default Safe Values 
    RegWrite = 0;
    MemRead  = 0;
    MemWrite = 0;
    MemtoReg = 0;
    ALUSrc   = 0;
    Branch   = 0;
    ALUOp    = 2'b00;

    //  Control Logic 
    case (opcode)
  
        // R-Type (0110011)
        7'b0110011: begin
            RegWrite = 1;
            ALUSrc   = 0;
            ALUOp    = 2'b10;
        end

        // I-Type ALU (0010011)
        7'b0010011: begin
            RegWrite = 1;
            ALUSrc   = 1;
            ALUOp    = 2'b10;
        end

        // LOAD (0000011)
        7'b0000011: begin
            RegWrite = 1;
            MemRead  = 1;
            MemtoReg = 1;
            ALUSrc   = 1;
            ALUOp    = 2'b00;  // address calculation (ADD)
        end

        // STORE (0100011)
        7'b0100011: begin
            MemWrite = 1;
            ALUSrc   = 1;
            ALUOp    = 2'b00;  // address calculation (ADD)
        end

        // BRANCH (1100011)
        7'b1100011: begin
            Branch = 1;
            ALUOp  = 2'b01;   // subtract for comparison
        end

        default: begin
            // already safe due to defaults
        end

    endcase

end

endmodule

immediateGen.v
module immediateGen
(
input [31:0] instruction,
output reg [31:0] immediate
);

always@(*)begin

case(instruction[6:0])
    7'b0010011, 7'b0000011:
        immediate = {{20{instruction[31]}}, instruction[31:20]};
    7'b0100011:
        immediate = {{20{instruction[31]}}, instruction[31:25], instruction[11:7]};
    7'b1100011:
        immediate = {{19{instruction[31]}}, instruction[7], instruction[30:25], instruction[11:8], 1'b0};
    default: immediate = 32'b0;
endcase
end 
endmodule

instructionMemo.v
module instructionMemory(
    input  [31:0] add,
    output reg [31:0] instruction
);

    // 256 words = 1KB of instruction memory
    // program.mem must be in the same directory as your simulation run
    reg [31:0] mem [0:255];

    initial begin
        $readmemh("program.mem", mem);
    end

    always @(*) begin
        instruction = mem[add >> 2];  // byte address → word index
    end

endmodule

src/pc_counter.v
module pc_counter
(
input clk,
input zeroflag,
input Branch,
input [31:0]branchTarget,
input reset,
output  reg [31:0]PcNxt);


always@(posedge clk)begin
    if(reset)begin
        PcNxt<=32'hFFFFFFFC;
    end
    else if (Branch  && zeroflag ) begin
        PcNxt <= branchTarget;
    end
    else if (Branch && !zeroflag ) begin
        PcNxt <= branchTarget;
    end
else begin
     PcNxt <= PcIn + 4;
end
end
endmodule

riscTop.v
module riscTop(
input clk,
input reset
);

wire [31:0] PcNxt;
wire [31:0] instruction;
wire [31:0] immediate;
wire [31:0] rs1_Value;
wire [31:0] rs2_Value;
wire [31:0] ALUResult;
wire [31:0] read_data ;
wire [31:0] branchTarget;
wire [31:0] WriteData;
wire [4:0] rd_addr;
wire [4:0] r1_addr;
wire [4:0] r2_addr;
wire [3:0] sel;
wire [2:0] funct3;
wire [1:0] ALUOp;
wire funct7;
wire RegWrite;
wire MemRead;
wire MemWrite;
wire MemtoReg;
wire ALUSrc;
wire Branch;




wire zeroflag;
wire [6:0] opcode;


assign branchTarget = PcNxt + immediate;
assign WriteData = (MemtoReg) ? read_data : ALUResult;

pc_counter PC(
    .clk(clk),
    .reset(reset),
    .Branch(Branch),
    .zeroflag(zeroflag),
    .branchTarget(branchTarget),
    
    .PcNxt(PcNxt)       // output connected
);

instructionMemory InstructionMemoryInst(
    .add(PcNxt),
    .instruction(instruction) // output connected
);

immediateGen ImmediateGenInst(
    .instruction(instruction),
    .immediate(immediate) // output connected
);

decoder DecoderInst(
    .instruction(instruction),
    .opcode(opcode), // output connected
    .rd_addr(rd_addr),
    .funct3(funct3),
    .rs1_addr(r1_addr),
    .rs2_addr(r2_addr),
    .funct7(funct7),

    .RegWrite(RegWrite),
    .MemRead(MemRead),
    .MemWrite(MemWrite),
    .MemtoReg(MemtoReg),
    .ALUSrc(ALUSrc),
    .Branch(Branch),
    .ALUOp(ALUOp)

);

alu ALUInst(
    .rs1_Value(rs1_Value),
    .rs2_Value(rs2_Value),
    .immediate(immediate),
    .sel(sel),
    .AluSrc(ALUSrc),
    .zeroflag(zeroflag), // output connected
    .aluResult(ALUResult)

);

AluControl AluControlInst(
    .ALUOp(ALUOp),
    .funct3(funct3),
    .funct7(funct7),  
    .sel(sel) // output connected
);

registerFile registerFileInst   (
    .rs1_addr(r1_addr),
    .rs2_addr(r2_addr),
    .rd_addr(rd_addr),
    .clk(clk),
    .WriteData(WriteData),
    .RegWrite(RegWrite),

    .ReadData1(rs1_Value),   // output connected
    .ReadData2(rs2_Value) 
);

DataMemo DataMemoInst (
    .clk(clk),
    .mem_read(MemRead),
    .mem_write(MemWrite),
    .address(ALUResult),
    .write_data(rs2_Value),
    .read_data(read_data)  
);
    
endmodule

tb/riscTopTB.v
`timescale 1ps/1ps

module TB_riscTop;
    reg clk;
    reg reset;

    riscTop dut(
        .clk(clk),
        .reset(reset)
    );

    always #5 clk = ~clk;
        always @(posedge clk) begin
    $display("PC=%0d | instr=%h | imm=%h | aluResult=%h | rd=%0d | RegWrite=%b | rs1_value = %b | sel=%b |b=%b",
        dut.PC.PcNxt,
        dut.InstructionMemoryInst.instruction,
        dut.ImmediateGenInst.immediate,
        dut.ALUInst.aluResult,
        dut.DecoderInst.rd_addr,
        dut.DecoderInst.RegWrite,
        dut.ALUInst.rs1_Value,
        dut.AluControlInst.sel,
        dut.ALUInst.b
        );
end
    initial begin
        clk   = 0;
        reset = 1;

        $dumpfile("riscTopTB.vcd");
        $dumpvars(0, TB_riscTop);

        // hold reset 3 cycles
        #30;
        reset = 0;

        // wait 10 cycles for 5 instructions to complete
        #200;

        $display("x1 = %0d", dut.registerFileInst.registers[1]);
        $display("x2 = %0d", dut.registerFileInst.registers[2]);
        $display("x3 = %0d", dut.registerFileInst.registers[3]);
        $display("x4 = %0d", dut.registerFileInst.registers[4]);
        $display("x5 = %0d", dut.registerFileInst.registers[5]);
        $display("x6 = %0d", dut.registerFileInst.registers[6]);
        $display("x7 = %0d", dut.registerFileInst.registers[7]);
        $display("x8 = %0d", dut.registerFileInst.registers[8]);
        $display("x9 = %0d", dut.registerFileInst.registers[9]);
        $display("x10 = %0d", dut.registerFileInst.registers[10]);
        $display("x11= %0d", $signed(dut.registerFileInst.registers[11]));
        $display("x12= %0d", $signed(dut.registerFileInst.registers[12]));
        $display("x13= %0d", $signed(dut.registerFileInst.registers[13]));
  
        $display("imm        = %h", dut.ImmediateGenInst.immediate);
        $display("ALU b      = %h", dut.ALUInst.b);
        $display("ALU result = %h", dut.ALUInst.aluResult);
        $display("WriteData  = %h", dut.WriteData);
        $display("x11 raw    = %h", dut.registerFileInst.registers[11]);
        $display("PC = %0d", dut.PC.PcNxt);
        $display("ALU b = %h", dut.ALUInst.b);

        $finish;
    end

endmodule

riscTopTB.vcd
$date
	Sat Aug 01 18:00:19 2026
$end
$version
	Icarus Verilog
$end
$timescale
	1ps
$end
$scope module TB_riscTop $end
$var reg 1 ! clk $end
$var reg 1 " reset $end
$scope module dut $end
$var wire 1 ! clk $end
$var wire 1 " reset $end
$var wire 1 # zeroflag $end
$var wire 4 $ sel [3:0] $end
$var wire 32 % rs2_Value [31:0] $end
$var wire 32 & rs1_Value [31:0] $end
$var wire 32 ' read_data [31:0] $end
$var wire 5 ( rd_addr [4:0] $end
$var wire 5 ) r2_addr [4:0] $end
$var wire 5 * r1_addr [4:0] $end
$var wire 7 + opcode [6:0] $end
$var wire 32 , instruction [31:0] $end
$var wire 32 - immediate [31:0] $end
$var wire 1 . funct7 $end
$var wire 3 / funct3 [2:0] $end
$var wire 32 0 branchTarget [31:0] $end
$var wire 32 1 WriteData [31:0] $end
$var wire 1 2 RegWrite $end
$var wire 32 3 PcNxt [31:0] $end
$var wire 1 4 MemtoReg $end
$var wire 1 5 MemWrite $end
$var wire 1 6 MemRead $end
$var wire 1 7 Branch $end
$var wire 1 8 ALUSrc $end
$var wire 32 9 ALUResult [31:0] $end
$var wire 2 : ALUOp [1:0] $end
$scope module ALUInst $end
$var wire 4 ; sel [3:0] $end
$var wire 32 < rs2_Value [31:0] $end
$var wire 32 = rs1_Value [31:0] $end
$var wire 32 > immediate [31:0] $end
$var wire 32 ? b [31:0] $end
$var wire 1 8 AluSrc $end
$var reg 32 @ aluResult [31:0] $end
$var reg 1 # zeroflag $end
$upscope $end
$scope module AluControlInst $end
$var wire 1 . funct7 $end
$var wire 3 A funct3 [2:0] $end
$var wire 1 8 ALUSrc $end
$var wire 2 B ALUOp [1:0] $end
$var reg 4 C sel [3:0] $end
$upscope $end
$scope module DataMemoInst $end
$var wire 32 D address [31:0] $end
$var wire 1 ! clk $end
$var wire 32 E write_data [31:0] $end
$var wire 32 F read_data [31:0] $end
$var wire 1 5 mem_write $end
$var wire 1 6 mem_read $end
$upscope $end
$scope module DecoderInst $end
$var wire 32 G instruction [31:0] $end
$var reg 2 H ALUOp [1:0] $end
$var reg 1 8 ALUSrc $end
$var reg 1 7 Branch $end
$var reg 1 6 MemRead $end
$var reg 1 5 MemWrite $end
$var reg 1 4 MemtoReg $end
$var reg 1 2 RegWrite $end
$var reg 3 I funct3 [2:0] $end
$var reg 1 . funct7 $end
$var reg 7 J opcode [6:0] $end
$var reg 5 K rd_addr [4:0] $end
$var reg 5 L rs1_addr [4:0] $end
$var reg 5 M rs2_addr [4:0] $end
$upscope $end
$scope module ImmediateGenInst $end
$var wire 32 N instruction [31:0] $end
$var reg 32 O immediate [31:0] $end
$upscope $end
$scope module InstructionMemoryInst $end
$var wire 32 P add [31:0] $end
$var reg 32 Q instruction [31:0] $end
$upscope $end
$scope module PC $end
$var wire 1 7 Branch $end
$var wire 32 R branchTarget [31:0] $end
$var wire 1 ! clk $end
$var wire 1 " reset $end
$var wire 1 # zeroflag $end
$var wire 32 S PcIn [31:0] $end
$var reg 32 T PcNxt [31:0] $end
$upscope $end
$scope module registerFileInst $end
$var wire 1 2 RegWrite $end
$var wire 32 U WriteData [31:0] $end
$var wire 1 ! clk $end
$var wire 5 V rd_addr [4:0] $end
$var wire 5 W rs1_addr [4:0] $end
$var wire 5 X rs2_addr [4:0] $end
$var reg 32 Y ReadData1 [31:0] $end
$var reg 32 Z ReadData2 [31:0] $end
$var integer 32 [ i [31:0] $end
$upscope $end
$upscope $end
$upscope $end
$enddefinitions $end
$comment Show the parameter values. $end
$dumpall
$end
#0
$dumpvars
b100000 [
bx Z
bx Y
bx X
bx W
bx V
bx U
bx T
bx S
bx R
bx Q
bx P
bx O
bx N
bx M
bx L
bx K
bx J
bx I
bx H
bx G
bx F
bx E
bx D
bx C
bx B
bx A
bx @
bx ?
bx >
bx =
bx <
bx ;
bx :
bx 9
x8
x7
x6
x5
x4
bx 3
x2
bx 1
bx 0
bx /
x.
bx -
bx ,
bx +
bx *
bx )
bx (
bx '
bx &
bx %
bx $
x#
1"
0!
$end
#5
b11111111111111111111111111111100 3
b11111111111111111111111111111100 P
b11111111111111111111111111111100 S
b11111111111111111111111111111100 T
1!
#10
0!
#15
1!
#20
0!
#25
1!
#30
0!
0"
#35
b101 1
b101 U
0#
b101 9
b101 @
b101 D
b101 ?
b0 '
b0 F
b0 %
b0 <
b0 E
b0 Z
b0 &
b0 =
b0 Y
b0 $
b0 ;
b0 C
b10 :
b10 B
b10 H
07
18
04
05
06
12
0.
b101 )
b101 M
b101 X
b0 *
b0 L
b0 W
b0 /
b0 A
b0 I
b1 (
b1 K
b1 V
b10011 +
b10011 J
b101 0
b101 R
b101 -
b101 >
b101 O
b10100000000000010010011 ,
b10100000000000010010011 G
b10100000000000010010011 N
b10100000000000010010011 Q
b0 3
b0 P
b0 S
b0 T
1!
#40
0!
#45
b11 1
b11 U
b11 9
b11 @
b11 D
b11 ?
b10 :
b10 B
b10 H
18
12
b11 )
b11 M
b11 X
b10 (
b10 K
b10 V
b11 -
b11 >
b11 O
b1100000000000100010011 ,
b1100000000000100010011 G
b1100000000000100010011 N
b1100000000000100010011 Q
b111 0
b111 R
b100 3
b100 P
b100 S
b100 T
1!
#50
0!
#55
b111 1
b111 U
b111 9
b111 @
b111 D
b101 &
b101 =
b101 Y
b11 $
b11 ;
b11 C
b110 ?
b10 :
b10 B
b10 H
18
12
b110 )
b110 M
b110 X
b1 *
b1 L
b1 W
b110 /
b110 A
b110 I
b11 (
b11 K
b11 V
b110 -
b110 >
b110 O
b11000001110000110010011 ,
b11000001110000110010011 G
b11000001110000110010011 N
b11000001110000110010011 Q
b1110 0
b1110 R
b1000 3
b1000 P
b1000 S
b1000 T
1!
#60
0!
#65
b100 1
b100 U
b100 9
b100 @
b100 D
b10 $
b10 ;
b10 C
b10 :
b10 B
b10 H
18
12
b111 /
b111 A
b111 I
b100 (
b100 K
b100 V
b11000001111001000010011 ,
b11000001111001000010011 G
b11000001111001000010011 N
b11000001111001000010011 Q
b10010 0
b10010 R
b1100 3
b1100 P
b1100 S
b1100 T
1!
#70
0!
#75
b11 1
b11 U
b11 9
b11 @
b11 D
b100 $
b100 ;
b100 C
b10 :
b10 B
b10 H
18
12
b100 /
b100 A
b100 I
b101 (
b101 K
b101 V
b11000001100001010010011 ,
b11000001100001010010011 G
b11000001100001010010011 N
b11000001100001010010011 Q
b10110 0
b10110 R
b10000 3
b10000 P
b10000 S
b10000 T
1!
#80
0!
#85
b1 1
b1 U
b1 9
b1 @
b1 D
b1000 $
b1000 ;
b1000 C
b1001 ?
b10 :
b10 B
b10 H
18
12
b1001 )
b1001 M
b1001 X
b10 /
b10 A
b10 I
b110 (
b110 K
b110 V
b1001 -
b1001 >
b1001 O
b100100001010001100010011 ,
b100100001010001100010011 G
b100100001010001100010011 N
b100100001010001100010011 Q
b11101 0
b11101 R
b10100 3
b10100 P
b10100 S
b10100 T
1!
#90
0!
#95
b0 1
b0 U
1#
b0 9
b0 @
b0 D
b11 %
b11 <
b11 E
b11 Z
b10 ?
b10 :
b10 B
b10 H
18
12
b10 )
b10 M
b10 X
b111 (
b111 K
b111 V
b10 -
b10 >
b10 O
b1000001010001110010011 ,
b1000001010001110010011 G
b1000001010001110010011 N
b1000001010001110010011 Q
b11010 0
b11010 R
b11000 3
b11000 P
b11000 S
b11000 T
1!
#100
0!
#105
b1 1
b1 U
0#
b1 9
b1 @
b1 D
b0 %
b0 <
b0 E
b0 Z
b1001 $
b1001 ;
b1001 C
b1001 ?
b10 :
b10 B
b10 H
18
12
b1001 )
b1001 M
b1001 X
b11 /
b11 A
b11 I
b1000 (
b1000 K
b1000 V
b1001 -
b1001 >
b1001 O
b100100001011010000010011 ,
b100100001011010000010011 G
b100100001011010000010011 N
b100100001011010000010011 Q
b100101 0
b100101 R
b11100 3
b11100 P
b11100 S
b11100 T
1!
#110
0!
#115
b10100 1
b10100 U
b10100 9
b10100 @
b10100 D
b11 %
b11 <
b11 E
b11 Z
b101 $
b101 ;
b101 C
b10 ?
b10 :
b10 B
b10 H
18
12
b10 )
b10 M
b10 X
b1 /
b1 A
b1 I
b1001 (
b1001 K
b1001 V
b10 -
b10 >
b10 O
b1000001001010010010011 ,
b1000001001010010010011 G
b1000001001010010010011 N
b1000001001010010010011 Q
b100010 0
b100010 R
b100000 3
b100000 P
b100000 S
b100000 T
1!
#120
0!
#125
b10 1
b10 U
b10 9
b10 @
b10 D
b101 %
b101 <
b101 E
b101 Z
b110 $
b110 ;
b110 C
b1 ?
b10 :
b10 B
b10 H
18
12
b1 )
b1 M
b1 X
b101 /
b101 A
b101 I
b1010 (
b1010 K
b1010 V
b1 -
b1 >
b1 O
b100001101010100010011 ,
b100001101010100010011 G
b100001101010100010011 N
b100001101010100010011 Q
b100101 0
b100101 R
b100100 3
b100100 P
b100100 S
b100100 T
1!
#130
0!
#135
b11111111111111111111111111111000 1
b11111111111111111111111111111000 U
b11111111111111111111111111111000 9
b11111111111111111111111111111000 @
b11111111111111111111111111111000 D
b0 %
b0 <
b0 E
b0 Z
b0 &
b0 =
b0 Y
b0 $
b0 ;
b0 C
b11111111111111111111111111111000 ?
b10 :
b10 B
b10 H
18
12
1.
b11000 )
b11000 M
b11000 X
b0 *
b0 L
b0 W
b0 /
b0 A
b0 I
b1011 (
b1011 K
b1011 V
b11111111111111111111111111111000 -
b11111111111111111111111111111000 >
b11111111111111111111111111111000 O
b11111111100000000000010110010011 ,
b11111111100000000000010110010011 G
b11111111100000000000010110010011 N
b11111111100000000000010110010011 Q
b100000 0
b100000 R
b101000 3
b101000 P
b101000 S
b101000 T
1!
#140
0!
#145
b11111111111111111111111111111100 1
b11111111111111111111111111111100 U
b11111111111111111111111111111100 9
b11111111111111111111111111111100 @
b11111111111111111111111111111100 D
b101 %
b101 <
b101 E
b101 Z
b11111111111111111111111111111000 &
b11111111111111111111111111111000 =
b11111111111111111111111111111000 Y
b111 $
b111 ;
b111 C
b10000000001 ?
b10 :
b10 B
b10 H
18
12
b1 )
b1 M
b1 X
b1011 *
b1011 L
b1011 W
b101 /
b101 A
b101 I
b1100 (
b1100 K
b1100 V
b10000000001 -
b10000000001 >
b10000000001 O
b1000000000101011101011000010011 ,
b1000000000101011101011000010011 G
b1000000000101011101011000010011 N
b1000000000101011101011000010011 Q
b10000101101 0
b10000101101 R
b101100 3
b101100 P
b101100 S
b101100 T
1!
#150
0!
#155
b1111111111111111111111111111100 1
b1111111111111111111111111111100 U
b1111111111111111111111111111100 9
b1111111111111111111111111111100 @
b1111111111111111111111111111100 D
b110 $
b110 ;
b110 C
b1 ?
b10 :
b10 B
b10 H
18
12
0.
b1101 (
b1101 K
b1101 V
b1 -
b1 >
b1 O
b101011101011010010011 ,
b101011101011010010011 G
b101011101011010010011 N
b101011101011010010011 Q
b110001 0
b110001 R
b110000 3
b110000 P
b110000 S
b110000 T
1!
#160
0!
#165
bx 1
bx U
x#
bx 9
bx @
bx D
bx %
bx <
bx E
bx Z
bx &
bx =
bx Y
b0 $
b0 ;
b0 C
bx ?
b0 :
b0 B
b0 H
08
02
x.
bx )
bx M
bx X
bx *
bx L
bx W
bx /
bx A
bx I
bx (
bx K
bx V
bx +
bx J
b0 -
b0 >
b0 O
bx ,
bx G
bx N
bx Q
b110100 0
b110100 R
b110100 3
b110100 P
b110100 S
b110100 T
1!
#170
0!
#175
b111000 0
b111000 R
b111000 3
b111000 P
b111000 S
b111000 T
1!
#180
0!
#185
b111100 0
b111100 R
b111100 3
b111100 P
b111100 S
b111100 T
1!
#190
0!
#195
b1000000 0
b1000000 R
b1000000 3
b1000000 P
b1000000 S
b1000000 T
1!
#200
0!
#205
b1000100 0
b1000100 R
b1000100 3
b1000100 P
b1000100 S
b1000100 T
1!
#210
0!
#215
b1001000 0
b1001000 R
b1001000 3
b1001000 P
b1001000 S
b1001000 T
1!
#220
0!
#225
b1001100 0
b1001100 R
b1001100 3
b1001100 P
b1001100 S
b1001100 T
1!
