src/DataMemo.v
module DataMemo (
    input  clk,
    input  mem_read,
    input  mem_write,
    input [31:0] address,
    input [31:0] write_data,
    output [31:0] read_data
);

    reg [31:0] mem [0:1023];

    // Asynchronous read
    assign read_data = (mem_read) ? mem[address[11:2]] : 32'b0;

    // Synchronous write
    always @(posedge clk) begin
        if (mem_write)
            mem[address[11:2]] <= write_data;
    end

endmodule

registerFile.v
module registerFile 
(
input [4:0] rs1_addr,
input [4:0] rs2_addr,
input [4:0] rd_addr,
input clk,
input [31:0] WriteData,
input RegWrite,

output reg[31:0] ReadData1,
output reg[31:0] ReadData2

);

reg [31:0] registers [0:31];
//making each register empty initially so no garbage value is thrown generally good practice

integer i;
initial begin
    for(i=0; i<32;i=i+1)begin
        registers[i]=0;
    end    
end
//combinational part
always@(*)begin
    ReadData1= registers[rs1_addr];
    ReadData2= registers[rs2_addr];
end
//sequential part 
always@(posedge clk)begin
    if(RegWrite && rd_addr != 5'd0)begin
        registers[rd_addr] <= WriteData;
    end
end

endmodule

src/AluControl.v
module AluControl
(
    input [1:0] ALUOp,
    input [2:0] funct3,
    input funct7,
    output reg [3:0]sel
);

always@(*)begin

    case(ALUOp)
    2'b00 : sel = 4'd0; // ADD
    2'b01 : sel = 4'd1; // SUB

    2'b10 : case(funct3)

    3'b000 : sel = (funct7) ? 4'd1 : 4'd0;// ADD if funct7 is 0 else sub
    3'b111 : sel = 4'd2; // AND
    3'b110 : sel = 4'd3; // OR
    3'b100 : sel = 4'd4; // XOR
    3'b001 : sel = 4'd5; // shift left
    3'b101 : sel = (funct7)? 4'd7 : 4'd6;//if funct7 0 then SRL else SRA
    3'b010 : sel = 4'd8; //SLT

    default : sel = 4'd0;

endcase

    default : sel = 0;

endcase

end

endmodule

alu.v
module alu(
    input  [31:0] rs1_Value,
    input  [31:0] rs2_Value,
    input  [31:0] immediate,
    input  [3:0]  sel,        // changed to 4 bits
    input         AluSrc,
    output reg    zeroflag,
    output reg [31:0] aluResult
);

    wire [31:0] b;

    assign b = (AluSrc == 1'b0) ? rs2_Value : immediate;

    always @(*) begin
        case(sel)

            4'd0:  aluResult = rs1_Value + b;        // add
            4'd1:  aluResult = rs1_Value - b;        // sub
            4'd2:  aluResult = rs1_Value & b;        // and
            4'd3:  aluResult = rs1_Value | b;        // or
            4'd4:  aluResult = rs1_Value ^ b;        // xor
            4'd5:  aluResult = rs1_Value << b[4:0];       // shift left by 4
            4'd6:  aluResult = rs1_Value >> b[4:0];      // shift right by 4 srl
            4'd7: aluResult=($signed(rs1_Value)) >>> b[4:0]   ;       // SRA shift right arithmatic
            4'd8: aluResult=($signed(rs1_Value)<$signed(b))? 32'd1:32'd0;       // SLT set less than
            
            default: aluResult = 32'd0;

        endcase

        zeroflag = (aluResult == 32'd0);

    end

endmodule

decoder.v
module decoder(
    input  [31:0] instruction,

    output reg [6:0] opcode,
    output reg [4:0] rd_addr,
    output reg [2:0] funct3,
    output reg [4:0] rs1_addr,
    output reg [4:0] rs2_addr,
    output reg funct7,

    output reg RegWrite,
    output reg MemRead,
    output reg MemWrite,
    output reg MemtoReg,
    output reg ALUSrc,
    output reg Branch,
    output reg [1:0] ALUOp
);

always @(*) begin

    // Field Extraction 
    opcode = instruction[6:0];
    rd_addr     = instruction[11:7];
    funct3 = instruction[14:12];
    rs1_addr    = instruction[19:15];
    rs2_addr    = instruction[24:20];
    funct7 = instruction[30];

    //  Default Safe Values 
    RegWrite = 0;
    MemRead  = 0;
    MemWrite = 0;
    MemtoReg = 0;
    ALUSrc   = 0;
    Branch   = 0;
    ALUOp    = 2'b00;

    //  Control Logic 
    case (opcode)
  
        // R-Type (0110011)
        7'b0110011: begin
            RegWrite = 1;
            ALUSrc   = 0;
            ALUOp    = 2'b10;
        end

        // I-Type ALU (0010011)
        7'b0010011: begin
            RegWrite = 1;
            ALUSrc   = 1;
            ALUOp    = 2'b10;
        end

        // LOAD (0000011)
        7'b0000011: begin
            RegWrite = 1;
            MemRead  = 1;
            MemtoReg = 1;
            ALUSrc   = 1;
            ALUOp    = 2'b00;  // address calculation (ADD)
        end

        // STORE (0100011)
        7'b0100011: begin
            MemWrite = 1;
            ALUSrc   = 1;
            ALUOp    = 2'b00;  // address calculation (ADD)
        end

        // BRANCH (1100011)
        7'b1100011: begin
            Branch = 1;
            ALUOp  = 2'b01;   // subtract for comparison
        end

        default: begin
            // already safe due to defaults
        end

    endcase

end

endmodule

immediateGen.v
module immediateGen
(
input [31:0] instruction,
output reg [31:0] immediate
);

always@(*)begin

case(instruction[6:0])
    7'b0010011, 7'b0000011:
        immediate = {{20{instruction[31]}}, instruction[31:20]};
    7'b0100011:
        immediate = {{20{instruction[31]}}, instruction[31:25], instruction[11:7]};
    7'b1100011:
        immediate = {{19{instruction[31]}}, instruction[7], instruction[30:25], instruction[11:8], 1'b0};
    default: immediate = 32'b0;
endcase
end 
endmodule

instructionMemo.v
module instructionMemory(
    input  [31:0] add,
    output reg [31:0] instruction
);

    // 256 words = 1KB of instruction memory
    // program.mem must be in the same directory as your simulation run
    reg [31:0] mem [0:255];

    initial begin
        $readmemh("program.mem", mem);
    end

    always @(*) begin
        instruction = mem[add >> 2];  // byte address → word index
    end

endmodule

src/pc_counter.v
module pc_counter
(input [31:0]PcIn,
input clk,
input zeroflag,
input Branch,
input [31:0]branchTarget,
input reset,
output  reg [31:0]PcNxt);


always@(posedge clk)begin
    if(reset)begin
        PcNxt<=32'hFFFFFFFC;
    end
    else if (Branch == 1 && zeroflag == 1) begin
        PcNxt <= branchTarget;
    end
else begin
     PcNxt <= PcIn + 4;
end
end
endmodule

riscTop.v
module riscTop(
input clk,
input reset
);

wire [31:0] PcNxt;
wire [31:0] instruction;
wire [31:0] immediate;
wire [31:0] rs1_Value;
wire [31:0] rs2_Value;
wire [31:0] ALUResult;
wire [31:0] read_data ;
wire [31:0] branchTarget;
wire [31:0] WriteData;
wire [4:0] rd_addr;
wire [4:0] r1_addr;
wire [4:0] r2_addr;
wire [3:0] sel;
wire [2:0] funct3;
wire [1:0] ALUOp;
wire funct7;
wire RegWrite;
wire MemRead;
wire MemWrite;
wire MemtoReg;
wire ALUSrc;
wire Branch;




wire zeroflag;
wire [6:0] opcode;


assign branchTarget = PcNxt + immediate;
assign WriteData = (MemtoReg) ? read_data : ALUResult;

pc_counter PC(
    .clk(clk),
    .reset(reset),
    .Branch(Branch),
    .zeroflag(zeroflag),
    .branchTarget(branchTarget),
    
    .PcNxt(PcNxt)       // output connected
);

instructionMemory InstructionMemoryInst(
    .add(PcNxt),
    .instruction(instruction) // output connected
);

immediateGen ImmediateGenInst(
    .instruction(instruction),
    .immediate(immediate) // output connected
);

decoder DecoderInst(
    .instruction(instruction),
    .opcode(opcode), // output connected
    .rd_addr(rd_addr),
    .funct3(funct3),
    .rs1_addr(r1_addr),
    .rs2_addr(r2_addr),
    .funct7(funct7),

    .RegWrite(RegWrite),
    .MemRead(MemRead),
    .MemWrite(MemWrite),
    .MemtoReg(MemtoReg),
    .ALUSrc(ALUSrc),
    .Branch(Branch),
    .ALUOp(ALUOp)

);

alu ALUInst(
    .rs1_Value(rs1_Value),
    .rs2_Value(rs2_Value),
    .immediate(immediate),
    .sel(sel),
    .AluSrc(ALUSrc),
    .zeroflag(zeroflag), // output connected
    .aluResult(ALUResult)

);

AluControl AluControlInst(
    .ALUOp(ALUOp),
    .funct3(funct3),
    .funct7(funct7),  
    .sel(sel) // output connected
);

registerFile registerFileInst   (
    .rs1_addr(r1_addr),
    .rs2_addr(r2_addr),
    .rd_addr(rd_addr),
    .clk(clk),
    .WriteData(WriteData),
    .RegWrite(RegWrite),

    .ReadData1(rs1_Value),   // output connected
    .ReadData2(rs2_Value) 
);

DataMemo DataMemoInst (
    .clk(clk),
    .mem_read(MemRead),
    .mem_write(MemWrite),
    .address(ALUResult),
    .write_data(rs2_Value),
    .read_data(read_data)  
);
    
endmodule

riscTopTB.v
`timescale 1ps/1ps

module TB_riscTop; 
    reg clk;
    reg reset;

    riscTop dut(
        .clk(clk),
        .reset(reset)
    );

    
    always #5 clk = ~clk;

    initial begin
        clk=0;

        $dumpfile("riscTopTB.vcd");
        $dumpvars(0,TB_riscTop);
        
        #2
        reset=1;
       #22
        reset=0;
        #222
        $display("x1 = %0d", dut.registerFileInst.registers[1]);
        $display("x2 = %0d", dut.registerFileInst.registers[2]);
        $display("x1 after instruction 1= %0d", dut.registerFileInst.registers[1]);
        $display("x3 = %0d", dut.registerFileInst.registers[3]);
        $display("x4 = %0d", dut.registerFileInst.registers[4]);
       
        $display("PC after run = %0d", dut.PC.PcNxt);
        $display("instruction at 0 = %h", dut.InstructionMemoryInst.instruction);

        $finish;
        
    end

    
endmodule

riscTopTB.vcd
$date
	Sun Mar 29 13:33:28 2026
$end
$version
	Icarus Verilog
$end
$timescale
	1ps
$end
$scope module TB_riscTop $end
$var reg 1 ! clk $end
$var reg 1 " reset $end
$scope module dut $end
$var wire 1 ! clk $end
$var wire 1 " reset $end
$var wire 1 # zeroflag $end
$var wire 4 $ sel [3:0] $end
$var wire 32 % rs2_Value [31:0] $end
$var wire 32 & rs1_Value [31:0] $end
$var wire 32 ' read_data [31:0] $end
$var wire 5 ( rd_addr [4:0] $end
$var wire 5 ) r2_addr [4:0] $end
$var wire 5 * r1_addr [4:0] $end
$var wire 7 + opcode [6:0] $end
$var wire 32 , instruction [31:0] $end
$var wire 32 - immediate [31:0] $end
$var wire 1 . funct7 $end
$var wire 3 / funct3 [2:0] $end
$var wire 32 0 branchTarget [31:0] $end
$var wire 32 1 WriteData [31:0] $end
$var wire 1 2 RegWrite $end
$var wire 32 3 PcNxt [31:0] $end
$var wire 1 4 MemtoReg $end
$var wire 1 5 MemWrite $end
$var wire 1 6 MemRead $end
$var wire 1 7 Branch $end
$var wire 1 8 ALUSrc $end
$var wire 32 9 ALUResult [31:0] $end
$var wire 2 : ALUOp [1:0] $end
$scope module ALUInst $end
$var wire 4 ; sel [3:0] $end
$var wire 32 < rs2_Value [31:0] $end
$var wire 32 = rs1_Value [31:0] $end
$var wire 32 > immediate [31:0] $end
$var wire 32 ? b [31:0] $end
$var wire 1 8 AluSrc $end
$var reg 32 @ aluResult [31:0] $end
$var reg 1 # zeroflag $end
$upscope $end
$scope module AluControlInst $end
$var wire 1 . funct7 $end
$var wire 3 A funct3 [2:0] $end
$var wire 2 B ALUOp [1:0] $end
$var reg 4 C sel [3:0] $end
$upscope $end
$scope module DataMemoInst $end
$var wire 32 D address [31:0] $end
$var wire 1 ! clk $end
$var wire 32 E write_data [31:0] $end
$var wire 32 F read_data [31:0] $end
$var wire 1 5 mem_write $end
$var wire 1 6 mem_read $end
$upscope $end
$scope module DecoderInst $end
$var wire 32 G instruction [31:0] $end
$var reg 2 H ALUOp [1:0] $end
$var reg 1 8 ALUSrc $end
$var reg 1 7 Branch $end
$var reg 1 6 MemRead $end
$var reg 1 5 MemWrite $end
$var reg 1 4 MemtoReg $end
$var reg 1 2 RegWrite $end
$var reg 3 I funct3 [2:0] $end
$var reg 1 . funct7 $end
$var reg 7 J opcode [6:0] $end
$var reg 5 K rd_addr [4:0] $end
$var reg 5 L rs1_addr [4:0] $end
$var reg 5 M rs2_addr [4:0] $end
$upscope $end
$scope module ImmediateGenInst $end
$var wire 32 N instruction [31:0] $end
$var reg 32 O immediate [31:0] $end
$upscope $end
$scope module InstructionMemoryInst $end
$var wire 32 P add [31:0] $end
$var reg 32 Q instruction [31:0] $end
$upscope $end
$scope module PC $end
$var wire 1 7 Branch $end
$var wire 32 R branchTarget [31:0] $end
$var wire 1 ! clk $end
$var wire 1 " reset $end
$var wire 1 # zeroflag $end
$var wire 32 S PcIn [31:0] $end
$var reg 32 T PcNxt [31:0] $end
$upscope $end
$scope module registerFileInst $end
$var wire 1 2 RegWrite $end
$var wire 32 U WriteData [31:0] $end
$var wire 1 ! clk $end
$var wire 5 V rd_addr [4:0] $end
$var wire 5 W rs1_addr [4:0] $end
$var wire 5 X rs2_addr [4:0] $end
$var reg 32 Y ReadData1 [31:0] $end
$var reg 32 Z ReadData2 [31:0] $end
$var integer 32 [ i [31:0] $end
$upscope $end
$upscope $end
$upscope $end
$enddefinitions $end
$comment Show the parameter values. $end
$dumpall
$end
#0
$dumpvars
b100000 [
bx Z
bx Y
bx X
bx W
bx V
bx U
bx T
bx S
bx R
bx Q
bx P
bx O
bx N
bx M
bx L
bx K
bx J
bx I
bx H
bx G
bx F
bx E
bx D
bx C
bx B
bx A
bx @
bx ?
bx >
bx =
bx <
bx ;
bx :
bx 9
x8
x7
x6
x5
x4
bx 3
x2
bx 1
bx 0
bx /
x.
bx -
bx ,
bx +
bx *
bx )
bx (
bx '
bx &
bx %
bx $
x#
x"
0!
$end
#2
1"
#5
b0 1
b0 U
1#
b0 9
b0 @
b0 D
b0 ?
b0 '
b0 F
b0 %
b0 <
b0 E
b0 Z
b0 &
b0 =
b0 Y
b0 $
b0 ;
b0 C
b0 :
b0 B
b0 H
07
08
04
05
06
02
0.
b0 )
b0 M
b0 X
b0 *
b0 L
b0 W
b0 /
b0 A
b0 I
b0 (
b0 K
b0 V
b0 +
b0 J
b11111111111111111111111111111100 0
b11111111111111111111111111111100 R
b0 -
b0 >
b0 O
b0 ,
b0 G
b0 N
b0 Q
b11111111111111111111111111111100 3
b11111111111111111111111111111100 P
b11111111111111111111111111111100 S
b11111111111111111111111111111100 T
1!
#10
0!
#15
1!
#20
0!
#24
0"
#25
b101 1
b101 U
0#
b101 9
b101 @
b101 D
b101 ?
b10 :
b10 B
b10 H
18
12
b101 )
b101 M
b101 X
b1 (
b1 K
b1 V
b10011 +
b10011 J
b101 -
b101 >
b101 O
b10100000000000010010011 ,
b10100000000000010010011 G
b10100000000000010010011 N
b10100000000000010010011 Q
b101 0
b101 R
b0 3
b0 P
b0 S
b0 T
1!
#30
0!
#35
b11 1
b11 U
b11 9
b11 @
b11 D
b11 ?
b10 :
b10 B
b10 H
18
12
b11 )
b11 M
b11 X
b10 (
b10 K
b10 V
b11 -
b11 >
b11 O
b1100000000000100010011 ,
b1100000000000100010011 G
b1100000000000100010011 N
b1100000000000100010011 Q
b111 0
b111 R
b100 3
b100 P
b100 S
b100 T
1!
#40
0!
#45
b1000 1
b1000 U
b1000 9
b1000 @
b1000 D
b11 %
b11 <
b11 E
b11 Z
b101 &
b101 =
b101 Y
b11 ?
b10 :
b10 B
b10 H
08
12
b10 )
b10 M
b10 X
b1 *
b1 L
b1 W
b11 (
b11 K
b11 V
b110011 +
b110011 J
b0 -
b0 >
b0 O
b1000001000000110110011 ,
b1000001000000110110011 G
b1000001000000110110011 N
b1000001000000110110011 Q
b1000 0
b1000 R
b1000 3
b1000 P
b1000 S
b1000 T
1!
#50
0!
#55
b10 1
b10 U
b10 9
b10 @
b10 D
b1 $
b1 ;
b1 C
b10 :
b10 B
b10 H
12
1.
b100 (
b100 K
b100 V
b1000000001000001000001000110011 ,
b1000000001000001000001000110011 G
b1000000001000001000001000110011 N
b1000000001000001000001000110011 Q
b1100 0
b1100 R
b1100 3
b1100 P
b1100 S
b1100 T
1!
#60
0!
#65
b1 1
b1 U
b1 9
b1 @
b1 D
b10 $
b10 ;
b10 C
b10 :
b10 B
b10 H
12
0.
b111 /
b111 A
b111 I
b101 (
b101 K
b101 V
b1000001111001010110011 ,
b1000001111001010110011 G
b1000001111001010110011 N
b1000001111001010110011 Q
b10000 0
b10000 R
b10000 3
b10000 P
b10000 S
b10000 T
1!
#70
0!
#75
1#
b0 1
b0 U
b0 ?
b0 9
b0 @
b0 D
b1000 %
b1000 <
b1000 E
b1000 Z
b0 &
b0 =
b0 Y
b0 $
b0 ;
b0 C
18
15
b0 :
b0 B
b0 H
02
b11 )
b11 M
b11 X
b0 *
b0 L
b0 W
b10 /
b10 A
b10 I
b0 (
b0 K
b0 V
b100011 +
b100011 J
b1100000010000000100011 ,
b1100000010000000100011 G
b1100000010000000100011 N
b1100000010000000100011 Q
b10100 0
b10100 R
b10100 3
b10100 P
b10100 S
b10100 T
1!
#80
0!
#85
b1000 1
b1000 U
b1000 '
b1000 F
b0 %
b0 <
b0 E
b0 Z
14
16
12
18
05
b0 )
b0 M
b0 X
b110 (
b110 K
b110 V
b11 +
b11 J
b10001100000011 ,
b10001100000011 G
b10001100000011 N
b10001100000011 Q
b11000 0
b11000 R
b11000 3
b11000 P
b11000 S
b11000 T
1!
#90
0!
#95
0#
b10 9
b10 @
b10 D
b10 1
b10 U
b0 '
b0 F
b11 %
b11 <
b11 E
b11 Z
b101 &
b101 =
b101 Y
b1 $
b1 ;
b1 C
b11 ?
b1 :
b1 B
b1 H
17
08
04
06
02
b10 )
b10 M
b10 X
b1 *
b1 L
b1 W
b0 /
b0 A
b0 I
b1000 (
b1000 K
b1000 V
b1100011 +
b1100011 J
b1000 -
b1000 >
b1000 O
b1000001000010001100011 ,
b1000001000010001100011 G
b1000001000010001100011 N
b1000001000010001100011 Q
b100100 0
b100100 R
b11100 3
b11100 P
b11100 S
b11100 T
1!
#100
0!
#105
b101 1
b101 U
b101 ?
b101 9
b101 @
b101 D
b0 $
b0 ;
b0 C
b1 %
b1 <
b1 E
b1 Z
b0 &
b0 =
b0 Y
18
12
b10 :
b10 B
b10 H
07
b101 )
b101 M
b101 X
b0 *
b0 L
b0 W
b10 (
b10 K
b10 V
b10011 +
b10011 J
b101 -
b101 >
b101 O
b10100000000000100010011 ,
b10100000000000100010011 G
b10100000000000100010011 N
b10100000000000100010011 Q
b100101 0
b100101 R
b100000 3
b100000 P
b100000 S
b100000 T
1!
#110
0!
#115
1#
b0 1
b0 U
b0 9
b0 @
b0 D
b1 $
b1 ;
b1 C
b101 %
b101 <
b101 E
b101 Z
b101 &
b101 =
b101 Y
b101 ?
17
b1 :
b1 B
b1 H
08
02
1.
b10 )
b10 M
b10 X
b1 *
b1 L
b1 W
b11101 (
b11101 K
b11101 V
b1100011 +
b1100011 J
b11111111111111111111111111111100 -
b11111111111111111111111111111100 >
b11111111111111111111111111111100 O
b11111110001000001000111011100011 ,
b11111110001000001000111011100011 G
b11111110001000001000111011100011 N
b11111110001000001000111011100011 Q
b100000 0
b100000 R
b100100 3
b100100 P
b100100 S
b100100 T
1!
#120
0!
#125
b101 1
b101 U
0#
b101 9
b101 @
b101 D
b0 $
b0 ;
b0 C
b1 %
b1 <
b1 E
b1 Z
b0 &
b0 =
b0 Y
18
12
b10 :
b10 B
b10 H
07
0.
b101 )
b101 M
b101 X
b0 *
b0 L
b0 W
b10 (
b10 K
b10 V
b10011 +
b10011 J
b101 -
b101 >
b101 O
b10100000000000100010011 ,
b10100000000000100010011 G
b10100000000000100010011 N
b10100000000000100010011 Q
b100101 0
b100101 R
b100000 3
b100000 P
b100000 S
b100000 T
1!
#130
0!
#135
1#
b0 1
b0 U
b0 9
b0 @
b0 D
b1 $
b1 ;
b1 C
b101 %
b101 <
b101 E
b101 Z
b101 &
b101 =
b101 Y
b101 ?
17
b1 :
b1 B
b1 H
08
02
1.
b10 )
b10 M
b10 X
b1 *
b1 L
b1 W
b11101 (
b11101 K
b11101 V
b1100011 +
b1100011 J
b11111111111111111111111111111100 -
b11111111111111111111111111111100 >
b11111111111111111111111111111100 O
b11111110001000001000111011100011 ,
b11111110001000001000111011100011 G
b11111110001000001000111011100011 N
b11111110001000001000111011100011 Q
b100000 0
b100000 R
b100100 3
b100100 P
b100100 S
b100100 T
1!
#140
0!
#145
b101 1
b101 U
0#
b101 9
b101 @
b101 D
b0 $
b0 ;
b0 C
b1 %
b1 <
b1 E
b1 Z
b0 &
b0 =
b0 Y
18
12
b10 :
b10 B
b10 H
07
0.
b101 )
b101 M
b101 X
b0 *
b0 L
b0 W
b10 (
b10 K
b10 V
b10011 +
b10011 J
b101 -
b101 >
b101 O
b10100000000000100010011 ,
b10100000000000100010011 G
b10100000000000100010011 N
b10100000000000100010011 Q
b100101 0
b100101 R
b100000 3
b100000 P
b100000 S
b100000 T
1!
#150
0!
#155
1#
b0 1
b0 U
b0 9
b0 @
b0 D
b1 $
b1 ;
b1 C
b101 %
b101 <
b101 E
b101 Z
b101 &
b101 =
b101 Y
b101 ?
17
b1 :
b1 B
b1 H
08
02
1.
b10 )
b10 M
b10 X
b1 *
b1 L
b1 W
b11101 (
b11101 K
b11101 V
b1100011 +
b1100011 J
b11111111111111111111111111111100 -
b11111111111111111111111111111100 >
b11111111111111111111111111111100 O
b11111110001000001000111011100011 ,
b11111110001000001000111011100011 G
b11111110001000001000111011100011 N
b11111110001000001000111011100011 Q
b100000 0
b100000 R
b100100 3
b100100 P
b100100 S
b100100 T
1!
#160
0!
#165
b101 1
b101 U
0#
b101 9
b101 @
b101 D
b0 $
b0 ;
b0 C
b1 %
b1 <
b1 E
b1 Z
b0 &
b0 =
b0 Y
18
12
b10 :
b10 B
b10 H
07
0.
b101 )
b101 M
b101 X
b0 *
b0 L
b0 W
b10 (
b10 K
b10 V
b10011 +
b10011 J
b101 -
b101 >
b101 O
b10100000000000100010011 ,
b10100000000000100010011 G
b10100000000000100010011 N
b10100000000000100010011 Q
b100101 0
b100101 R
b100000 3
b100000 P
b100000 S
b100000 T
1!
#170
0!
#175
1#
b0 1
b0 U
b0 9
b0 @
b0 D
b1 $
b1 ;
b1 C
b101 %
b101 <
b101 E
b101 Z
b101 &
b101 =
b101 Y
b101 ?
17
b1 :
b1 B
b1 H
08
02
1.
b10 )
b10 M
b10 X
b1 *
b1 L
b1 W
b11101 (
b11101 K
b11101 V
b1100011 +
b1100011 J
b11111111111111111111111111111100 -
b11111111111111111111111111111100 >
b11111111111111111111111111111100 O
b11111110001000001000111011100011 ,
b11111110001000001000111011100011 G
b11111110001000001000111011100011 N
b11111110001000001000111011100011 Q
b100000 0
b100000 R
b100100 3
b100100 P
b100100 S
b100100 T
1!
#180
0!
#185
b101 1
b101 U
0#
b101 9
b101 @
b101 D
b0 $
b0 ;
b0 C
b1 %
b1 <
b1 E
b1 Z
b0 &
b0 =
b0 Y
18
12
b10 :
b10 B
b10 H
07
0.
b101 )
b101 M
b101 X
b0 *
b0 L
b0 W
b10 (
b10 K
b10 V
b10011 +
b10011 J
b101 -
b101 >
b101 O
b10100000000000100010011 ,
b10100000000000100010011 G
b10100000000000100010011 N
b10100000000000100010011 Q
b100101 0
b100101 R
b100000 3
b100000 P
b100000 S
b100000 T
1!
#190
0!
#195
1#
b0 1
b0 U
b0 9
b0 @
b0 D
b1 $
b1 ;
b1 C
b101 %
b101 <
b101 E
b101 Z
b101 &
b101 =
b101 Y
b101 ?
17
b1 :
b1 B
b1 H
08
02
1.
b10 )
b10 M
b10 X
b1 *
b1 L
b1 W
b11101 (
b11101 K
b11101 V
b1100011 +
b1100011 J
b11111111111111111111111111111100 -
b11111111111111111111111111111100 >
b11111111111111111111111111111100 O
b11111110001000001000111011100011 ,
b11111110001000001000111011100011 G
b11111110001000001000111011100011 N
b11111110001000001000111011100011 Q
b100000 0
b100000 R
b100100 3
b100100 P
b100100 S
b100100 T
1!
#200
0!
#205
b101 1
b101 U
0#
b101 9
b101 @
b101 D
b0 $
b0 ;
b0 C
b1 %
b1 <
b1 E
b1 Z
b0 &
b0 =
b0 Y
18
12
b10 :
b10 B
b10 H
07
0.
b101 )
b101 M
b101 X
b0 *
b0 L
b0 W
b10 (
b10 K
b10 V
b10011 +
b10011 J
b101 -
b101 >
b101 O
b10100000000000100010011 ,
b10100000000000100010011 G
b10100000000000100010011 N
b10100000000000100010011 Q
b100101 0
b100101 R
b100000 3
b100000 P
b100000 S
b100000 T
1!
#210
0!
#215
1#
b0 1
b0 U
b0 9
b0 @
b0 D
b1 $
b1 ;
b1 C
b101 %
b101 <
b101 E
b101 Z
b101 &
b101 =
b101 Y
b101 ?
17
b1 :
b1 B
b1 H
08
02
1.
b10 )
b10 M
b10 X
b1 *
b1 L
b1 W
b11101 (
b11101 K
b11101 V
b1100011 +
b1100011 J
b11111111111111111111111111111100 -
b11111111111111111111111111111100 >
b11111111111111111111111111111100 O
b11111110001000001000111011100011 ,
b11111110001000001000111011100011 G
b11111110001000001000111011100011 N
b11111110001000001000111011100011 Q
b100000 0
b100000 R
b100100 3
b100100 P
b100100 S
b100100 T
1!
#220
0!
#225
b101 1
b101 U
0#
b101 9
b101 @
b101 D
b0 $
b0 ;
b0 C
b1 %
b1 <
b1 E
b1 Z
b0 &
b0 =
b0 Y
18
12
b10 :
b10 B
b10 H
07
0.
b101 )
b101 M
b101 X
b0 *
b0 L
b0 W
b10 (
b10 K
b10 V
b10011 +
b10011 J
b101 -
b101 >
b101 O
b10100000000000100010011 ,
b10100000000000100010011 G
b10100000000000100010011 N
b10100000000000100010011 Q
b100101 0
b100101 R
b100000 3
b100000 P
b100000 S
b100000 T
1!
#230
0!
#235
1#
b0 1
b0 U
b0 9
b0 @
b0 D
b1 $
b1 ;
b1 C
b101 %
b101 <
b101 E
b101 Z
b101 &
b101 =
b101 Y
b101 ?
17
b1 :
b1 B
b1 H
08
02
1.
b10 )
b10 M
b10 X
b1 *
b1 L
b1 W
b11101 (
b11101 K
b11101 V
b1100011 +
b1100011 J
b11111111111111111111111111111100 -
b11111111111111111111111111111100 >
b11111111111111111111111111111100 O
b11111110001000001000111011100011 ,
b11111110001000001000111011100011 G
b11111110001000001000111011100011 N
b11111110001000001000111011100011 Q
b100000 0
b100000 R
b100100 3
b100100 P
b100100 S
b100100 T
1!
#240
0!
#245
b101 1
b101 U
0#
b101 9
b101 @
b101 D
b0 $
b0 ;
b0 C
b1 %
b1 <
b1 E
b1 Z
b0 &
b0 =
b0 Y
18
12
b10 :
b10 B
b10 H
07
0.
b101 )
b101 M
b101 X
b0 *
b0 L
b0 W
b10 (
b10 K
b10 V
b10011 +
b10011 J
b101 -
b101 >
b101 O
b10100000000000100010011 ,
b10100000000000100010011 G
b10100000000000100010011 N
b10100000000000100010011 Q
b100101 0
b100101 R
b100000 3
b100000 P
b100000 S
b100000 T
1!
#250
0!
#255
1#
b0 1
b0 U
b0 9
b0 @
b0 D
b1 $
b1 ;
b1 C
b101 %
b101 <
b101 E
b101 Z
b101 &
b101 =
b101 Y
b101 ?
17
b1 :
b1 B
b1 H
08
02
1.
b10 )
b10 M
b10 X
b1 *
b1 L
b1 W
b11101 (
b11101 K
b11101 V
b1100011 +
b1100011 J
b11111111111111111111111111111100 -
b11111111111111111111111111111100 >
b11111111111111111111111111111100 O
b11111110001000001000111011100011 ,
b11111110001000001000111011100011 G
b11111110001000001000111011100011 N
b11111110001000001000111011100011 Q
b100000 0
b100000 R
b100100 3
b100100 P
b100100 S
b100100 T
1!
#260
0!
#265
b101 1
b101 U
0#
b101 9
b101 @
b101 D
b0 $
b0 ;
b0 C
b1 %
b1 <
b1 E
b1 Z
b0 &
b0 =
b0 Y
18
12
b10 :
b10 B
b10 H
07
0.
b101 )
b101 M
b101 X
b0 *
b0 L
b0 W
b10 (
b10 K
b10 V
b10011 +
b10011 J
b101 -
b101 >
b101 O
b10100000000000100010011 ,
b10100000000000100010011 G
b10100000000000100010011 N
b10100000000000100010011 Q
b100101 0
b100101 R
b100000 3
b100000 P
b100000 S
b100000 T
1!
